LICENSE
README.md
setup.cfg
setup.py
dir2docker.egg-info/PKG-INFO
dir2docker.egg-info/SOURCES.txt
dir2docker.egg-info/dependency_links.txt
dir2docker.egg-info/not-zip-safe
dir2docker.egg-info/requires.txt
dir2docker.egg-info/top_level.txt
directory2docker/__init__.py
directory2docker/app.py